profiles_local/__init__.py
profiles_local/comprehensive_profile.py
profiles_local/constants_profiles_local.py
profiles_local/profiles_local.py
profiles_local-0.0.71.dist-info/METADATA
profiles_local-0.0.71.dist-info/WHEEL
profiles_local-0.0.71.dist-info/top_level.txt
profiles_local-0.0.71.dist-info/RECORD
